{"is_source_file": false, "format": "", "description": "", "external_files": [], "external_methods": [], "published": [], "classes": [], "methods": [], "calls": [], "search-terms": [], "state": 2, "file_id": 3, "knowledge_revision": 46, "git_revision": "0f9d41ae5bfe0610af13cca8082cc69ffa89deb6", "hash": "f679af3bf99545b5f3d13024622a9107", "format-version": 4, "code-base-name": "notes_frontend", "filename": "notes_frontend/README.md", "revision_history": [{"46": "0f9d41ae5bfe0610af13cca8082cc69ffa89deb6"}]}